{
  "bpm": 120,
  "length_in_beats": 16,
  "voices": {
    "closed_hihat": [
      0.0,
      2.0,
      3.0,
      4.0,
      6.0,
      7.0,
      8.0,
      10.0,
      11.0,
      12.0,
      14.0,
      15.0
    ],
    "snare": [
      0.0,
      2.0,
      5.0,
      7.0,
      9.0,
      12.0,
      14.0
    ],
    "kick": [
      0.0,
      3.0,
      4.0,
      7.0,
      8.0,
      11.0,
      12.0,
      15.0
    ],
    "open_hihat": [
      2.0,
      6.0,
      10.0,
      14.0
    ],
    "ride": [],
    "crash": []
  },
  "id": "9d5e400c-5e71-4e25-b935-128c2c26d4c2",
  "name": "samba"
}